llm_friendly/__init__.py
llm_friendly/aws/__init__.py
llm_friendly/aws/table_parser.py
llm_friendly/aws/textract.py
llm_friendly-0.1.1.dist-info/METADATA
llm_friendly-0.1.1.dist-info/WHEEL
llm_friendly-0.1.1.dist-info/RECORD
