Metadata-Version: 2.1
Name: llm-friendly
Version: 0.1.1
Summary: llm-friendly converts structured data to LLM-friendly text.
Author: Aniruddha ADHIKARY
Author-email: Aniruddha_ADHIKARY@tech.gov.sg
Requires-Python: >=3.10,<4.0
Classifier: Programming Language :: Python :: 3
Classifier: Programming Language :: Python :: 3.10
Classifier: Programming Language :: Python :: 3.11
